humphrey/__init__.py
humphrey-2026.0.dist-info/WHEEL
humphrey-2026.0.dist-info/METADATA
humphrey-2026.0.dist-info/RECORD
