Metadata-Version: 2.4
Name: humphrey
Version: 2026.0
Summary: An IRC client with no dependencies
Author: William Jackson
Author-email: William Jackson <william@subtlecoolness.com>
License-Expression: MIT
Classifier: Programming Language :: Python :: 3
Classifier: Operating System :: OS Independent
Requires-Python: >=3.10
Project-URL: Homepage, https://github.com/williamjacksn/humphrey
Project-URL: Issues, https://github.com/williamjacksn/humphrey/issues
